fetter/__init__.py
fetter/fetter.cpython-39-i386-linux-gnu.so
fetter-3.1.0.dist-info/METADATA
fetter-3.1.0.dist-info/WHEEL
fetter-3.1.0.dist-info/entry_points.txt
fetter-3.1.0.dist-info/licenses/LICENSE
fetter-3.1.0.dist-info/RECORD
