Metadata-Version: 2.4
Name: fetter
Version: 3.1.0
Classifier: Programming Language :: Rust
Classifier: Topic :: Security
License-File: LICENSE
Summary: System-wide Python package discovery, validation, and allow-listing.
Keywords: python-package,allow-listing,vulnerability scanning
Author: Christopher Ariza
Maintainer: Christopher Ariza
Requires-Python: >=3.9
Project-URL: Homepage, https://github.com/fetter-io/fetter-py
Project-URL: Issues, https://github.com/fetter-io/fetter-py/issues
Project-URL: Repository, https://github.com/fetter-io/fetter-py.git
